{
    "name": "exhsearch_s7_d3_num4",
    "maze_array": [
        "###|#.#|###|#.#|###|#.#|###|",
        "#..|#.#|...|#.#|...|..#|..#|",
        "#.#|#.#|#.#|#.#|#.#|###|#.#|",
        "---------------------------|",
        "###|#.#|###|###|###|#.#|###|",
        "#..|#.#|...|...|..#|#..|...|",
        "#.#|#.#|###|###|#.#|###|#.#|",
        "---------------------------|",
        "#.#|#.#|#.#|###|###|#.#|#.#|",
        "#..|#.#|#..|#..|...|#..|..#|",
        "#.#|#.#|#.#|#.#|#.#|#.#|#.#|",
        "---------------------------|",
        "###|###|###|#.#|#.#|###|#.#|",
        "...|#..|..#|..#|#..|...|#..|",
        "###|#.#|#.#|#.#|###|###|###|",
        "---------------------------|",
        "#.#|###|#.#|#.#|#.#|###|#.#|",
        "#..|...|...|#..|..#|...|..#|",
        "#.#|#.#|###|###|#.#|#.#|#.#|",
        "---------------------------|",
        "###|###|#.#|###|###|###|#.#|",
        "#..|#..|..#|...|...|..#|#..|",
        "#.#|#.#|###|###|###|#.#|###|",
        "---------------------------|",
        "#.#|#.#|#.#|###|#.#|###|#.#|",
        "#..|#.#|...|...|...|...|..#|",
        "###|#.#|###|###|###|###|###|",
        "---------------------------|"
    ],
    "leftover": "NES",
    "piece_locations": [
        {
            "row": 0,
            "column": 2
        }
    ],
    "objective": {
        "row": 4,
        "column": 5
    }
}