{
    "name": "minimax_s13_num53",
    "maze_array": [
        "###|#.#|###|###|###|###|###|#.#|###|###|###|###|###|",
        "#..|#..|...|..#|...|...|...|..#|...|..#|...|...|..#|",
        "#.#|###|#.#|#.#|#.#|###|#.#|#.#|#.#|#.#|#.#|###|#.#|",
        "---------------------------------------------------|",
        "#.#|#.#|###|#.#|#.#|#.#|#.#|#.#|#.#|###|#.#|#.#|#.#|",
        "..#|#..|#..|#.#|#..|#.#|..#|#.#|...|...|..#|#..|#..|",
        "###|###|#.#|#.#|#.#|#.#|###|#.#|###|###|###|###|###|",
        "---------------------------------------------------|",
        "#.#|#.#|#.#|#.#|###|#.#|###|###|###|###|###|#.#|#.#|",
        "#..|..#|#..|#.#|...|#.#|...|...|...|...|...|#..|..#|",
        "#.#|###|#.#|#.#|#.#|#.#|#.#|###|#.#|###|#.#|###|#.#|",
        "---------------------------------------------------|",
        "#.#|#.#|#.#|###|#.#|#.#|#.#|###|###|###|###|###|#.#|",
        "#.#|#.#|#.#|...|..#|#..|#.#|#..|..#|...|#..|...|#..|",
        "#.#|#.#|#.#|###|###|#.#|#.#|#.#|#.#|###|#.#|###|###|",
        "---------------------------------------------------|",
        "#.#|###|#.#|#.#|#.#|#.#|###|#.#|###|###|#.#|#.#|#.#|",
        "#..|#..|#..|..#|#..|#.#|...|..#|...|#..|..#|#..|..#|",
        "#.#|#.#|#.#|###|#.#|#.#|#.#|#.#|#.#|#.#|#.#|###|#.#|",
        "---------------------------------------------------|",
        "###|###|#.#|###|#.#|#.#|###|###|###|#.#|#.#|#.#|###|",
        "#..|...|..#|..#|#.#|#..|...|..#|#..|#.#|..#|..#|...|",
        "#.#|###|###|#.#|#.#|#.#|#.#|#.#|#.#|#.#|#.#|#.#|###|",
        "---------------------------------------------------|",
        "#.#|###|#.#|###|#.#|#.#|#.#|#.#|#.#|###|#.#|#.#|#.#|",
        "#..|...|#..|...|#..|#.#|...|#.#|..#|#..|..#|#.#|..#|",
        "#.#|###|#.#|###|#.#|#.#|#.#|#.#|#.#|#.#|#.#|#.#|#.#|",
        "---------------------------------------------------|",
        "###|###|#.#|#.#|#.#|#.#|###|#.#|###|###|#.#|###|###|",
        "...|...|#.#|..#|..#|#..|...|..#|#..|..#|#.#|...|...|",
        "###|###|#.#|###|###|###|###|###|#.#|#.#|#.#|###|###|",
        "---------------------------------------------------|",
        "#.#|#.#|#.#|#.#|#.#|#.#|#.#|#.#|#.#|#.#|#.#|#.#|#.#|",
        "#..|#..|#..|#.#|...|...|...|...|..#|#..|..#|..#|..#|",
        "#.#|###|#.#|#.#|###|###|###|###|#.#|#.#|#.#|###|#.#|",
        "---------------------------------------------------|",
        "#.#|#.#|#.#|###|#.#|###|#.#|#.#|#.#|#.#|#.#|#.#|#.#|",
        "#.#|#.#|#..|#..|#..|...|..#|#..|#.#|#..|#..|...|..#|",
        "#.#|#.#|###|#.#|###|###|###|###|#.#|###|#.#|###|#.#|",
        "---------------------------------------------------|",
        "#.#|#.#|#.#|###|#.#|###|#.#|#.#|#.#|#.#|#.#|#.#|#.#|",
        "#..|#.#|...|...|...|..#|...|...|...|#.#|..#|...|..#|",
        "#.#|#.#|###|###|###|#.#|###|###|###|#.#|#.#|###|#.#|",
        "---------------------------------------------------|",
        "#.#|#.#|###|###|#.#|###|#.#|#.#|###|#.#|###|#.#|#.#|",
        "#..|...|#..|...|#.#|#..|#..|#.#|..#|#.#|..#|..#|..#|",
        "#.#|###|#.#|#.#|#.#|#.#|###|#.#|#.#|#.#|#.#|###|#.#|",
        "---------------------------------------------------|",
        "#.#|###|#.#|#.#|#.#|#.#|#.#|###|#.#|#.#|#.#|###|#.#|",
        "#..|#..|...|#.#|...|..#|...|..#|...|#..|...|..#|..#|",
        "###|#.#|###|#.#|###|###|###|#.#|###|###|###|#.#|###|",
        "---------------------------------------------------|"
    ],
    "leftover": "NE",
    "piece_locations": [
        {
            "row": 3,
            "column": 10
        },
        {
            "row": 1,
            "column": 0
        }
    ],
    "objective": {
        "row": 11,
        "column": 4
    }
}